carad_display/__init__.py
carad_display/main.py
carad_display/utils/__init__.py
carad_display/utils/gps.py
carad_display/utils/json.py
carad_display/utils/metrics.py
carad_display/utils/videos.py
carad_display/videos/default_video.mp4
carad_display-0.9.2.dist-info/licenses/LICENSE
carad_display-0.9.2.dist-info/METADATA
carad_display-0.9.2.dist-info/WHEEL
carad_display-0.9.2.dist-info/entry_points.txt
carad_display-0.9.2.dist-info/top_level.txt
carad_display-0.9.2.dist-info/RECORD
