Metadata-Version: 2.4
Name: carad-display
Version: 0.9.2
Summary: A package for diplay of CARAD project, requires run on linux
Author-email: amgudym@mail.ru
Requires-Python: >=3.11
License-File: LICENSE
Requires-Dist: certifi==2025.4.26
Requires-Dist: cffi==1.17.1
Requires-Dist: charset-normalizer==3.4.2
Requires-Dist: cryptography==44.0.3
Requires-Dist: idna==3.10
Requires-Dist: numpy==2.2.5
Requires-Dist: opencv-python==4.11.0.86
Requires-Dist: paho-mqtt==2.1.0
Requires-Dist: pillow==11.2.1
Requires-Dist: pycparser==2.22
Requires-Dist: pygnssutils==1.1.13
Requires-Dist: pygpsclient==1.5.7
Requires-Dist: pynmea2==1.19.0
Requires-Dist: pynmeagps==1.0.50
Requires-Dist: pyrtcm==1.1.6
Requires-Dist: pyserial==3.5
Requires-Dist: pyspartn==1.0.5
Requires-Dist: python-vlc==3.0.21203
Requires-Dist: pyubx2==1.2.52
Requires-Dist: pyubxutils==1.0.3
Requires-Dist: requests==2.32.3
Requires-Dist: shapely==2.1.0
Requires-Dist: sparkfun-ublox-gps==1.1.5
Requires-Dist: spidev==3.7
Requires-Dist: spidriver==1.1.1
Requires-Dist: ublox==0.1.3
Requires-Dist: urllib3==2.4.0
Dynamic: author-email
Dynamic: description
Dynamic: description-content-type
Dynamic: license-file
Dynamic: requires-dist
Dynamic: requires-python
Dynamic: summary
